soundmonitor/__init__.py
soundmonitor/modules.py
soundmonitor/utilities.py
soundmonitor-0.0.2.dist-info/LICENSE
soundmonitor-0.0.2.dist-info/METADATA
soundmonitor-0.0.2.dist-info/WHEEL
soundmonitor-0.0.2.dist-info/top_level.txt
soundmonitor-0.0.2.dist-info/RECORD
