Metadata-Version: 2.1
Name: soundmonitor
Version: 0.0.2
Summary: Long-term sound level measurements analysis in Python
Author: Valérian Fraisse
Author-email: Valérian Fraisse <valerian.fraisse@mail.mcgill.ca>
Project-URL: Homepage, https://github.com/valerianF/soundmonitor
Project-URL: Bug Tracker, https://github.com/valerianF/soundmonitor/issues
Classifier: Programming Language :: Python :: 3
Classifier: License :: OSI Approved :: Apache Software License
Classifier: Operating System :: OS Independent
Requires-Python: >=3.7
License-File: LICENSE
Requires-Dist: matplotlib (>=3.5.3)
Requires-Dist: numpy (>=1.21.6)
Requires-Dist: pandas (>=1.3.5)
Requires-Dist: xlrd (>=2.0.1)
Requires-Dist: openpyxl (>=3.1.2)
